AICON-2.0.1.data/scripts/AICON
aicon/__init__.py
aicon/band.py
aicon/deformatpotent.py
aicon/dielectric.py
aicon/ekappa.py
aicon/elastic.py
aicon/electron.py
aicon/hallcoeff.py
aicon/myemc.py
aicon/myfiretasks.py
aicon/myfireworks.py
aicon/myworkflow.py
aicon/phonon.py
aicon/relaxtime.py
aicon/seebeck.py
aicon/tools.py
aicon/version.py
AICON-2.0.1.dist-info/LICENSE
AICON-2.0.1.dist-info/METADATA
AICON-2.0.1.dist-info/WHEEL
AICON-2.0.1.dist-info/top_level.txt
AICON-2.0.1.dist-info/RECORD
