Metadata-Version: 2.1
Name: AICON
Version: 2.0.1
Summary: This is the AICON module.
Home-page: https://github.com/Baijianlu/AICON2.git
Author: Tao Fan
Author-email: Tao.Fan@skoltech.ru
License: UNKNOWN
Platform: UNKNOWN
Classifier: Programming Language :: Python :: 3
Classifier: License :: OSI Approved :: GNU General Public License v3 (GPLv3)
Classifier: Operating System :: OS Independent
Provides: aicon
Requires-Python: >=3.6
License-File: LICENSE
Requires-Dist: numpy (>=1.17.2)
Requires-Dist: scipy (>=1.3.1)
Requires-Dist: pymatgen (>=2020.4.2)
Requires-Dist: atomate (>=0.9.4)
Requires-Dist: pymongo (>=3.10.1)
